odoo/addons/sale_product_set_sale_by_packaging/README.rst
odoo/addons/sale_product_set_sale_by_packaging/__init__.py
odoo/addons/sale_product_set_sale_by_packaging/__manifest__.py
odoo/addons/sale_product_set_sale_by_packaging/data/ir_cron.xml
odoo/addons/sale_product_set_sale_by_packaging/i18n/sale_product_set_sale_by_packaging.pot
odoo/addons/sale_product_set_sale_by_packaging/models/__init__.py
odoo/addons/sale_product_set_sale_by_packaging/models/product_product.py
odoo/addons/sale_product_set_sale_by_packaging/models/product_set_line.py
odoo/addons/sale_product_set_sale_by_packaging/models/product_template.py
odoo/addons/sale_product_set_sale_by_packaging/readme/CONTRIBUTORS.rst
odoo/addons/sale_product_set_sale_by_packaging/readme/DESCRIPTION.rst
odoo/addons/sale_product_set_sale_by_packaging/static/description/icon.png
odoo/addons/sale_product_set_sale_by_packaging/static/description/index.html
odoo/addons/sale_product_set_sale_by_packaging/tests/__init__.py
odoo/addons/sale_product_set_sale_by_packaging/tests/test_product_set_packaging.py
odoo/addons/sale_product_set_sale_by_packaging/views/product_set.xml
odoo/addons/sale_product_set_sale_by_packaging/views/product_set_line.xml
odoo/addons/sale_product_set_sale_by_packaging/views/product_template.xml
odoo13_addon_sale_product_set_sale_by_packaging-13.0.1.1.0.dist-info/METADATA
odoo13_addon_sale_product_set_sale_by_packaging-13.0.1.1.0.dist-info/WHEEL
odoo13_addon_sale_product_set_sale_by_packaging-13.0.1.1.0.dist-info/top_level.txt
odoo13_addon_sale_product_set_sale_by_packaging-13.0.1.1.0.dist-info/RECORD
