Metadata-Version: 2.1
Name: odoo13-addon-sale-product-set-sale-by-packaging
Version: 13.0.1.1.0
Summary: Glue module between `sale_by_packaging` and `sale_product_set_packaging_qty`.
Home-page: https://github.com/OCA/sale-workflow
Author: Camptocamp, Odoo Community Association (OCA)
Author-email: support@odoo-community.org
License: AGPL-3
Platform: UNKNOWN
Classifier: Programming Language :: Python
Classifier: Framework :: Odoo
Classifier: License :: OSI Approved :: GNU Affero General Public License v3
Classifier: Development Status :: 3 - Alpha
Requires-Python: >=3.5
Requires-Dist: odoo13-addon-sale-by-packaging
Requires-Dist: odoo13-addon-sale-product-set-packaging-qty
Requires-Dist: odoo (<13.1dev,>=13.0a)
